{
  "title": [
    "Dainyātmikā"
  ],
  "author": [
    "Śrīla Bhakti Vinod Ṭhākur"
  ],
  "subtitle": [],
  "verses": [
    {
      "number": "1",
      "text": [
        "(prabhu he!)",
        "emana durmati    saṁsāra bhitare",
        "    paḍiyā āchhinu āmi",
        "tava nija-jana        kona mahājane",
        "    pāṭhāiyā dile tumi"
      ],
      "translation": [
        "Una mentalidad mezquina me trajo a este mundo, ¡oh, Señor!, pero uno de Tus excelsos devotos puros vino para sacarme."
      ],
      "word_by_word": [
        "<i class=\"SongVerse__term\">prabhu he!</i> — ¡oh Señor!; <i class=\"SongVerse__term\">emona</i> — esta; <i class=\"SongVerse__term\">durmati</i> — mente malvada; <i class=\"SongVerse__term\">saṁsāra</i> — mundo material; <i class=\"SongVerse__term\">bhitare</i> — dentro; <i class=\"SongVerse__term\">paḍiyā</i> — cayendo; <i class=\"SongVerse__term\">achhinu</i> — soy; <i class=\"SongVerse__term\">āmi</i> — yo; <i class=\"SongVerse__term\">tava</i> — tuyo; <i class=\"SongVerse__term\">nija jana</i> — [Tu] propia gente; <i class=\"SongVerse__term\">kona</i> — algunos; <i class=\"SongVerse__term\">mahājane</i> — grandes personalidades exaltadas; <i class=\"SongVerse__term\">pāṭhāiyā</i> — envío; <i class=\"SongVerse__term\">dile</i> — dio; <i class=\"SongVerse__term\">tumi</i> — tú."
      ]
    },
    {
      "number": "2",
      "text": [
        "doyā kori more,    patita dekhiyā,",
        "    kohilo āmāre giyā",
        "ohe dīna-jon,        śuno bhālo kathā",
        "    ullasita ho’be hiyā"
      ],
      "translation": [
        "Me vio tan caído y desdichado, que tuvo compasión y vino a decirme: “¡Oh, alma humilde! Por favor, escucha estas buenas noticias, pues alegrarán tu corazón”."
      ],
      "word_by_word": [
        "<i class=\"SongVerse__term\">doyā</i> — misericordia; <i class=\"SongVerse__term\">kori</i> — hacer; <i class=\"SongVerse__term\">more</i> — sobre mí; <i class=\"SongVerse__term\">patita</i> — caído; <i class=\"SongVerse__term\">dekhiyā</i> — viendo; <i class=\"SongVerse__term\">kohilo</i> — dijo; <i class=\"SongVerse__term\">āmāre</i> — a mí; <i class=\"SongVerse__term\">giyā</i> — yendo; <i class=\"SongVerse__term\">ohe</i> — ¡oh!; <i class=\"SongVerse__term\">dīna-jana</i> — las personas pobres; <i class=\"SongVerse__term\">śuno</i> — escucha; <i class=\"SongVerse__term\">bhālo</i> — bueno; <i class=\"SongVerse__term\">kathā</i> — hechos; <i class=\"SongVerse__term\">ullasita</i> — entusiasta; <i class=\"SongVerse__term\">ha’be</i> — será; <i class=\"SongVerse__term\">hiyā</i> — corazón."
      ]
    },
    {
      "number": "3",
      "text": [
        "tomāre tārite        śrī-kṛṣṇa-chaitanya",
        "    navadvīpe avatāra",
        "tomā hena kata    dīna-hīna jane",
        "    karilena bhava-pāra"
      ],
      "translation": [
        "Śrī Kṛṣṇa Chaitanya apareció en la tierra de Nabadwīp para liberarte. Él ha conducido felizmente, más allá del océano de la existencia material, a muchas almas miserables como tú."
      ],
      "word_by_word": [
        "<i class=\"SongVerse__term\">tomāre</i> — a ti; <i class=\"SongVerse__term\">tārite</i> — entregar; <i class=\"SongVerse__term\">śrī-kṛṣṇa-chaitanya</i> — el Señor Śrī Kṛṣṇa Chaitanya; <i class=\"SongVerse__term\">navadwīpe</i> — en Nabadwīp; <i class=\"SongVerse__term\">avatār</i> — encarnación; <i class=\"SongVerse__term\">tomā</i> — a ti; <i class=\"SongVerse__term\">hena</i> — como en; <i class=\"SongVerse__term\">kata</i> — cuántos; <i class=\"SongVerse__term\">dīna hīna</i> — caído y desamparado; <i class=\"SongVerse__term\">jane</i> — gente; <i class=\"SongVerse__term\">karilena</i> — por favor hazlo; <i class=\"SongVerse__term\">bhava</i> — océano de miseria; <i class=\"SongVerse__term\">pāra</i> — cruza."
      ]
    },
    {
      "number": "4",
      "text": [
        "vedera pratijñā    rākhibāra tare",
        "    rukma-varṇa vipra-suta",
        "mahāprabhu nāme    nadīyā mātāya",
        "(mahāprabhu nāme    jagata mātāya)",
        "    saṅge bhāi avadhūta"
      ],
      "translation": [
        "Para cumplir la promesa de los <i class=\"SongVerse__term\">Vedas</i>, Él descendió con una tez dorada, como hijo de un <i class=\"SongVerse__term\">brāhmana</i>, llevando el nombre de Mahāprabhu, junto con Su hermano, el <i class=\"SongVerse__term\">avadhūta</i> Nityānanda. Ellos dos enloquecieron a todo Nadia (todo el mundo) con amor divino."
      ],
      "word_by_word": [
        "<i class=\"SongVerse__term\">vedera</i> — de los <i class=\"SongVerse__term\">Vedas</i>; <i class=\"SongVerse__term\">pratijñā</i> — promesa; <i class=\"SongVerse__term\">rākhibāra</i> — protector de; <i class=\"SongVerse__term\">tare</i> — con el fin de; <i class=\"SongVerse__term\">rukma</i> — dorado; <i class=\"SongVerse__term\">varṇa</i> — color; <i class=\"SongVerse__term\">vipra</i> — <i class=\"SongVerse__term\">br</i>ā<i class=\"SongVerse__term\">hmana</i>; <i class=\"SongVerse__term\">suta</i> — hijo; <i class=\"SongVerse__term\">mahāprabhu</i> — Mahāprahu (lit. Gran Señor); <i class=\"SongVerse__term\">nāme</i> — nombre; <i class=\"SongVerse__term\">nadīyā</i> — de Nadia; <i class=\"SongVerse__term\">jagata</i> — (el mundo); <i class=\"SongVerse__term\">mātāya</i> — intoxicado; <i class=\"SongVerse__term\">saṅge</i> — en asociación; <i class=\"SongVerse__term\">bhāi</i> — hermano; <i class=\"SongVerse__term\">avadhūta</i> — un nombre del Señor Nityananda (lit. el loco religioso)."
      ]
    },
    {
      "number": "5",
      "text": [
        "nanda suta jini    chaitanya gosāñī",
        "    nija-nāma kari’ dāna",
        "tārila jagat        tumi-o yāiyā",
        "    laha nija paritrāṇa"
      ],
      "translation": [
        "Śrī Chaitanya, quien es Kṛṣṇa Mismo, el hijo de Nanda, salvó al mundo al distribuir Su propio Santo Nombre. Tú, también, ve y obtén tu liberación."
      ],
      "word_by_word": [
        "<i class=\"SongVerse__term\">nanda suta</i> — hijo de Nanda Mahārāj; <i class=\"SongVerse__term\">jini</i> — de quien; <i class=\"SongVerse__term\">chaitanya</i> — Chaitanya Mahāprabhu; <i class=\"SongVerse__term\">gosāñi</i> — goswāmī; <i class=\"SongVerse__term\">nija</i> — propio; <i class=\"SongVerse__term\">nāma</i> — nombre; <i class=\"SongVerse__term\">kori</i> — <i class=\"SongVerse__term\">(yā)</i> — hacer; <i class=\"SongVerse__term\">dana</i> — dar; <i class=\"SongVerse__term\">tārila</i> — entregado; <i class=\"SongVerse__term\">jagat</i> — el mundo; <i class=\"SongVerse__term\">tumi</i> — tú; <i class=\"SongVerse__term\">o</i> — también; <i class=\"SongVerse__term\">jāiyā</i> — ve; <i class=\"SongVerse__term\">laha</i> — toma; <i class=\"SongVerse__term\">nija</i> — propio; <i class=\"SongVerse__term\">paritrana</i> — liberación."
      ]
    },
    {
      "number": "6",
      "text": [
        "se kathā śuniyā    āsiyāchhi, nātha!",
        "    tomāra charaṇa-tale",
        "bhakati-vinoda    kā̐diyā kā̐diyā",
        "    āpana-kāhinī bale"
      ],
      "translation": [
        "¡Oh Señor! Al escuchar esas palabras, Bhakti Vinod vino hasta las plantas de Tus pies de loto. Llorando, el narra la historia de su vida."
      ],
      "word_by_word": [
        "<i class=\"SongVerse__term\">se</i> — esto; <i class=\"SongVerse__term\">kathā</i> — palabras; <i class=\"SongVerse__term\">śuniyā</i> —  escuchar; <i class=\"SongVerse__term\">āsiyāchi</i> — venir; <i class=\"SongVerse__term\">nātha</i> — ¡oh Señor!; <i class=\"SongVerse__term\">tomāra</i> — tuyo; <i class=\"SongVerse__term\">charaṇa</i> — pies de loto; <i class=\"SongVerse__term\">tale</i> — plantas de los pies; <i class=\"SongVerse__term\">bhakativinoda</i> — Bhakti Vinoda Ṭhākur; <i class=\"SongVerse__term\">kā̐diyā kā̐diyā</i> — llorando y llorando; <i class=\"SongVerse__term\">āpana</i> — propio; <i class=\"SongVerse__term\">kāhinī</i> — historia; <i class=\"SongVerse__term\">bale</i> — dice."
      ]
    }
  ],
  "word_by_word": [
    "<i class=\"SongVerse__term\">dainya</i> — humildad; <i class=\"SongVerse__term\">atmikā</i> — resoluta."
  ],
  "attributes": {
    "page": "174"
  }
}